filesignature/__init__.py
filesignature/collector.py
filesignature/filesignature.py
filesignature/models.py
filesignature-0.1.3.dist-info/METADATA
filesignature-0.1.3.dist-info/WHEEL
filesignature-0.1.3.dist-info/RECORD
