Metadata-Version: 2.1
Name: filesignature
Version: 0.1.3
Summary: File signature comparison tool, magic numbers.
Home-page: https://github.com/kurotom/filesignature
License: GPL-3.0-or-later
Keywords: filesignature,file signature,magicnumbers,magic numbers
Author: kurotom
Author-email: 55354389+kurotom@users.noreply.github.com
Requires-Python: >=3.7,<4.0
Classifier: License :: OSI Approved :: GNU General Public License v3 or later (GPLv3+)
Classifier: Programming Language :: Python :: 3
Classifier: Programming Language :: Python :: 3.7
Classifier: Programming Language :: Python :: 3.8
Classifier: Programming Language :: Python :: 3.9
Classifier: Programming Language :: Python :: 3.10
Classifier: Programming Language :: Python :: 3.11
Classifier: Topic :: File Formats
Requires-Dist: chardet (>=5.2.0,<6.0.0)
Requires-Dist: filesignaturecollectors (>=0.1.7,<0.2.0)
Project-URL: Bug Tracker, https://github.com/kurotom/filesignature/issues
Project-URL: Repository, https://github.com/kurotom/filesignature
